job_performance_analyzer/__init__.py
job_performance_analyzer/__main__.py
job_performance_analyzer/analyze_job.py
job_performance_analyzer/analyzers/__init__.py
job_performance_analyzer/analyzers/base_analyzer.py
job_performance_analyzer/analyzers/incremental_analyzer.py
job_performance_analyzer/core/__init__.py
job_performance_analyzer/core/aligner.py
job_performance_analyzer/core/parser.py
job_performance_analyzer/core/reporter.py
job_performance_analyzer/rules/__init__.py
job_performance_analyzer/rules/base_rule.py
job_performance_analyzer/rules/ap_mode/__init__.py
job_performance_analyzer/rules/common/__init__.py
job_performance_analyzer/rules/incremental/__init__.py
job_performance_analyzer/rules/incremental/stage_optimization/__init__.py
job_performance_analyzer/rules/incremental/stage_optimization/active_problem_finding.py
job_performance_analyzer/rules/incremental/stage_optimization/hash_join_optimization.py
job_performance_analyzer/rules/incremental/stage_optimization/max_dop_check.py
job_performance_analyzer/rules/incremental/stage_optimization/refresh_type_detection.py
job_performance_analyzer/rules/incremental/stage_optimization/single_dop_aggregate.py
job_performance_analyzer/rules/incremental/stage_optimization/spilling_analysis.py
job_performance_analyzer/rules/incremental/stage_optimization/tablesink_dop.py
job_performance_analyzer/rules/incremental/state_table/__init__.py
job_performance_analyzer/rules/incremental/state_table/aggregate_reuse.py
job_performance_analyzer/rules/incremental/state_table/append_only_scan.py
job_performance_analyzer/rules/incremental/state_table/heavy_calc_state.py
job_performance_analyzer/rules/incremental/state_table/incremental_algorithm_visualization.py
job_performance_analyzer/rules/incremental/state_table/non_incremental_diagnosis.py
job_performance_analyzer/rules/incremental/state_table/row_number_check.py
job_performance_analyzer/rules/incremental/state_table/state_table_enable.py
clickzetta_skills-1.0.4.dist-info/METADATA
clickzetta_skills-1.0.4.dist-info/WHEEL
clickzetta_skills-1.0.4.dist-info/entry_points.txt
clickzetta_skills-1.0.4.dist-info/RECORD
