Metadata-Version: 2.4
Name: clickzetta-skills
Version: 1.0.4
Summary: Clickzetta 系统技能工具集 - 包含性能分析、诊断等专业工具
Author: Clickzetta Team
License-Expression: Apache-2.0
Keywords: analyzer,clickzetta,diagnosis,optimization,performance,sql
Classifier: Development Status :: 4 - Beta
Classifier: Intended Audience :: Developers
Classifier: License :: OSI Approved :: Apache Software License
Classifier: Programming Language :: Python :: 3
Classifier: Programming Language :: Python :: 3.10
Classifier: Programming Language :: Python :: 3.11
Classifier: Programming Language :: Python :: 3.12
Requires-Python: >=3.6
Provides-Extra: dev
Requires-Dist: build; extra == 'dev'
Requires-Dist: pytest-asyncio; extra == 'dev'
Requires-Dist: pytest>=7.0.0; extra == 'dev'
Requires-Dist: twine; extra == 'dev'
